sawyer/__init__.py
sawyer/base.py
sawyer/door.py
sawyer/env_util.py
sawyer/flat_goal_env.py
sawyer/image_wrapper.py
sawyer/mixed_env.py
sawyer/mujoco_env.py
sawyer/multitask_env.py
sawyer/peg_3d.py
sawyer/pick_place.py
sawyer/sawyer/bottom_right_lighting.xml
sawyer/sawyer/front_left_lighting.xml
sawyer/sawyer/sawyer_door-1.xml
sawyer/sawyer/sawyer_door-2.xml
sawyer/sawyer/sawyer_door-3.xml
sawyer/sawyer/sawyer_mixed.xml
sawyer/sawyer/sawyer_peg_3d.xml
sawyer/sawyer/sawyer_pick_and_place-1.xml
sawyer/sawyer/sawyer_pick_and_place-2.xml
sawyer/sawyer/sawyer_pick_and_place-3.xml
sawyer/sawyer/sawyer_pick_and_place-4.xml
sawyer/sawyer/sawyer_xyz_base.xml
sawyer/sawyer/shared_config.xml
sawyer/sawyer/meshes/base.stl
sawyer/sawyer/meshes/eGripperBase.stl
sawyer/sawyer/meshes/head.stl
sawyer/sawyer/meshes/l0.stl
sawyer/sawyer/meshes/l1.stl
sawyer/sawyer/meshes/l2.stl
sawyer/sawyer/meshes/l3.stl
sawyer/sawyer/meshes/l4.stl
sawyer/sawyer/meshes/l5.stl
sawyer/sawyer/meshes/l6.stl
sawyer/sawyer/meshes/pedestal.stl
sawyer-0.0.1.dist-info/LICENSE
sawyer-0.0.1.dist-info/METADATA
sawyer-0.0.1.dist-info/WHEEL
sawyer-0.0.1.dist-info/top_level.txt
sawyer-0.0.1.dist-info/RECORD
