Metadata-Version: 2.1
Name: sawyer
Version: 0.0.1
Summary: gym-dmc
Home-page: https://github.com/geyang/gym-sawyer
Author: Ge Yang<ge.ike.yang@gmail.com>
Author-email: ge.ike.yang@gmail.com
License: UNKNOWN
Platform: UNKNOWN
Requires-Dist: gym
Requires-Dist: numpy
